argparse_extd/__init__.py
argparse_extd/argparse_extd.py
argparse_extd-0.0.4.dist-info/licenses/LICENSE
argparse_extd-0.0.4.dist-info/METADATA
argparse_extd-0.0.4.dist-info/WHEEL
argparse_extd-0.0.4.dist-info/top_level.txt
argparse_extd-0.0.4.dist-info/RECORD
