Metadata-Version: 2.4
Name: argparse-extd
Version: 0.0.4
Summary: Extended argparse.ArgumentParser and Extended argparse.Namespace
Home-page: https://github.com/nanigashi-uji/argparse-extd.git
Author: Nanigashi Uji
Author-email: 53845049+nanigashi-uji@users.noreply.github.com
License: BSD-3-Clause
Keywords: argparse extenstion
Classifier: Development Status :: 4 - Beta
Classifier: License :: OSI Approved :: BSD License
Classifier: Programming Language :: Python
Classifier: Programming Language :: Python :: 3
Classifier: Topic :: Software Development :: Libraries :: Python Modules
Classifier: Topic :: System :: Software Distribution
Classifier: Topic :: Utilities
License-File: LICENSE
Requires-Dist: pkgstruct
Requires-Dist: PyYAML
Requires-Dist: toml
Dynamic: author
Dynamic: author-email
Dynamic: classifier
Dynamic: description
Dynamic: home-page
Dynamic: keywords
Dynamic: license
Dynamic: license-file
Dynamic: requires-dist
Dynamic: summary
